<?xml version="1.0" encoding="UTF-8"?>
<objects serializationModel="Studio.02.01.00">
	<object class="Workspace" id="{9328cc6f-b478-4973-9b88-1f366567d13a}">
		<relationship name="masterEventFolder">
			<destination>{00051e0a-9581-425b-b24c-6ecc08e5ef6f}</destination>
		</relationship>
		<relationship name="masterTagFolder">
			<destination>{15ec84cc-a7fa-4920-81af-bfc8a67a8b94}</destination>
		</relationship>
		<relationship name="masterEffectPresetFolder">
			<destination>{8cc88366-416d-4d5e-82f1-48da331ba17d}</destination>
		</relationship>
		<relationship name="masterParameterPresetFolder">
			<destination>{c76fd3ec-d99e-4d33-8996-ffbfb86f21d5}</destination>
		</relationship>
		<relationship name="masterBankFolder">
			<destination>{edf5b349-db9f-4f87-8eab-2bddcdb245c2}</destination>
		</relationship>
		<relationship name="masterSandboxFolder">
			<destination>{1d2548b2-5200-47b1-9434-8af2766adf11}</destination>
		</relationship>
		<relationship name="masterAssetFolder">
			<destination>{dcedfcf1-f017-4985-9a16-22df8f3f2c52}</destination>
		</relationship>
		<relationship name="mixer">
			<destination>{039d1ac4-2310-495c-9d02-9bbbc157effb}</destination>
		</relationship>
		<relationship name="profilerSessionFolder">
			<destination>{8aaedc72-aabb-479f-8f55-59bb79504229}</destination>
		</relationship>
		<relationship name="platforms">
			<destination>{26700742-cf4d-4835-b016-6884a47c7c49}</destination>
		</relationship>
	</object>
</objects>
